fileioapi/__init__.py
fileioapi-0.0.2.dist-info/LICENSE
fileioapi-0.0.2.dist-info/METADATA
fileioapi-0.0.2.dist-info/WHEEL
fileioapi-0.0.2.dist-info/top_level.txt
fileioapi-0.0.2.dist-info/RECORD
